{
  "db_name": "SQLite",
  "query": "SELECT id,name FROM notes_table WHERE name LIKE $1 ORDER BY name ASC",
  "describe": {
    "columns": [
      {
        "name": "id",
        "ordinal": 0,
        "type_info": "Integer"
      },
      {
        "name": "name",
        "ordinal": 1,
        "type_info": "Text"
      }
    ],
    "parameters": {
      "Right": 1
    },
    "nullable": [
      true,
      true
    ]
  },
  "hash": "c21a6f9fa7504e8e70ab6df0a8656ec2ec6bbc8a3640c01021a452820e101902"
}
